{"Name":"Raj","Age":28,"City":"Delhi","salary":50000,"performance_score":85}
{"Name":"Vivek","Age":34,"City":"Mumbai","salary":60000,"performance_score":90}
{"Name":"Ankita","Age":22,"City":"Bangalore","salary":45000,"performance_score":78}
{"Name":"Riya","Age":29,"City":"Chennai","salary":52000,"performance_score":88}
{"Name":"Sahil","Age":31,"City":"Kolkata","salary":58000,"performance_score":92}
{"Name":"Neha","Age":27,"City":"Hyderabad","salary":47000,"performance_score":80}
{"Name":"Arjun","Age":30,"City":"Pune","salary":62000,"performance_score":95}
{"Name":"Pooja","Age":26,"City":"Ahmedabad","salary":48000,"performance_score":83}
